fpsim/__init__.py
fpsim/analyzers.py
fpsim/arrays.py
fpsim/calibration.py
fpsim/defaults.py
fpsim/demographics.py
fpsim/education.py
fpsim/experiment.py
fpsim/fpmod.py
fpsim/interventions.py
fpsim/methods.py
fpsim/parameters.py
fpsim/people.py
fpsim/plotting.py
fpsim/scenarios.py
fpsim/settings.py
fpsim/sim.py
fpsim/utils.py
fpsim/version.py
fpsim/data_processing/country_codes.csv
fpsim/data_processing/DHS_PMA_scripts/dhs_parse_debutage.py
fpsim/data_processing/DHS_PMA_scripts/dhs_parse_mcprbyparity.py
fpsim/data_processing/UN_WB_data_scraping/UN_data_scraping.py
fpsim/data_processing/UN_WB_data_scraping/WorldBank_data_scraping.py
fpsim/locations/__init__.py
fpsim/locations/data_utils.py
fpsim/locations/cotedivore/data/debut_age.csv
fpsim/locations/cotedivore/data/mcpr_by_parity.csv
fpsim/locations/ethiopia/ethiopia.py
fpsim/locations/ethiopia/data/afb.table.csv
fpsim/locations/ethiopia/data/age_partnership.csv
fpsim/locations/ethiopia/data/age_pyramid.csv
fpsim/locations/ethiopia/data/ageparity.csv
fpsim/locations/ethiopia/data/asfr.csv
fpsim/locations/ethiopia/data/basic_wb.yaml
fpsim/locations/ethiopia/data/bf_stats.csv
fpsim/locations/ethiopia/data/birth_spacing_dhs.csv
fpsim/locations/ethiopia/data/birth_spacing_pref.csv
fpsim/locations/ethiopia/data/contra_coef_mid.csv
fpsim/locations/ethiopia/data/contra_coef_mid_pp1.csv
fpsim/locations/ethiopia/data/contra_coef_mid_pp6.csv
fpsim/locations/ethiopia/data/contra_coef_simple.csv
fpsim/locations/ethiopia/data/contra_coef_simple_pp1.csv
fpsim/locations/ethiopia/data/contra_coef_simple_pp6.csv
fpsim/locations/ethiopia/data/cpr.csv
fpsim/locations/ethiopia/data/debut_age.csv
fpsim/locations/ethiopia/data/edu_initialization.csv
fpsim/locations/ethiopia/data/edu_objective.csv
fpsim/locations/ethiopia/data/edu_stop.csv
fpsim/locations/ethiopia/data/education.csv
fpsim/locations/ethiopia/data/infant_mortality.csv
fpsim/locations/ethiopia/data/lam.csv
fpsim/locations/ethiopia/data/maternal_mortality.csv
fpsim-3.3.0.dist-info/licenses/LICENSE
fpsim-3.3.0.dist-info/METADATA
fpsim-3.3.0.dist-info/WHEEL
fpsim-3.3.0.dist-info/top_level.txt
fpsim-3.3.0.dist-info/RECORD
