Metadata-Version: 2.4
Name: fpsim
Version: 3.3.0
Summary: FPsim: Family Planning Simulator
Home-page: http://fpsim.org
Author: Michelle O'Brien, Annie Valente, Cliff Kerr, Sam Buxton, Daniel Klein, Marita Zimmermann, Emily Driano
Author-email: info@fpsim.org
Keywords: family planning,women's health,agent-based model,simulation
Platform: OS Independent
Classifier: Environment :: Console
Classifier: Intended Audience :: Science/Research
Classifier: License :: Other/Proprietary License
Classifier: Operating System :: OS Independent
Classifier: Programming Language :: Python
Classifier: Topic :: Software Development :: Libraries :: Python Modules
Classifier: Development Status :: 5 - Production/Stable
Classifier: Programming Language :: Python :: 3.10
License-File: LICENSE
Requires-Dist: numpy
Requires-Dist: numba
Requires-Dist: scipy
Requires-Dist: starsim>=3.0.2
Requires-Dist: pandas>=1.3
Requires-Dist: sciris>=2.1.0
Requires-Dist: matplotlib>=3.5.0
Requires-Dist: seaborn>=0.9
Requires-Dist: optuna
Requires-Dist: plotnine
Requires-Dist: pyarrow
Requires-Dist: pyyaml
Dynamic: author
Dynamic: author-email
Dynamic: classifier
Dynamic: description
Dynamic: description-content-type
Dynamic: home-page
Dynamic: keywords
Dynamic: license-file
Dynamic: platform
Dynamic: requires-dist
Dynamic: summary
